echolocator_api/__init__.py
echolocator_api/aiohttp_client.py
echolocator_api/exceptions.py
echolocator_api/databases/constants.py
echolocator_api/guis/__init__.py
echolocator_api/guis/aiohttp.py
echolocator_api/guis/constants.py
echolocator_api/guis/context.py
echolocator_api/guis/guis.py
echolocator_cli/__init__.py
echolocator_cli/main.py
echolocator_cli/version.py
echolocator_cli/subcommands/__init__.py
echolocator_cli/subcommands/base.py
echolocator_cli/subcommands/service.py
echolocator_lib/__init__.py
echolocator_lib/__main__.py
echolocator_lib/_version.py
echolocator_lib/base_aiohttp.py
echolocator_lib/envvar.py
echolocator_lib/version.py
echolocator_lib/composers/__init__.py
echolocator_lib/composers/composers.py
echolocator_lib/composers/html.py
echolocator_lib/composers/prettyhelper.py
echolocator_lib/composers/text.py
echolocator_lib/guis/__init__.py
echolocator_lib/guis/aiohttp.py
echolocator_lib/guis/base.py
echolocator_lib/guis/constants.py
echolocator_lib/guis/context.py
echolocator_lib/guis/guis.py
echolocator_lib/guis/html/index.html
echolocator_lib/guis/html/index.js
echolocator_lib/guis/html/css/image_edit_ux.css
echolocator_lib/guis/html/css/image_list_ux.css
echolocator_lib/guis/html/css/pixel_ux.css
echolocator_lib/guis/html/css/plate_list_ux.css
echolocator_lib/guis/html/css/styles.css
echolocator_lib/guis/html/css/system_health_ux.css
echolocator_lib/guis/html/css/images/dls_logo_50x50.png
echolocator_lib/guis/html/images/green_dot_crosshair.png
echolocator_lib/guis/html/images/radial1.666.png
echolocator_lib/guis/html/javascript/runtime.js
echolocator_lib/guis/html/javascript/version.js
echolocator_lib/guis/html/javascript/common/base.js
echolocator_lib/guis/html/javascript/echolocator/centroid_ux.js
echolocator_lib/guis/html/javascript/echolocator/events.js
echolocator_lib/guis/html/javascript/echolocator/image_edit_ux.js
echolocator_lib/guis/html/javascript/echolocator/image_list_ux.js
echolocator-1.6.0.dist-info/LICENSE
echolocator-1.6.0.dist-info/METADATA
echolocator-1.6.0.dist-info/WHEEL
echolocator-1.6.0.dist-info/entry_points.txt
echolocator-1.6.0.dist-info/top_level.txt
echolocator-1.6.0.dist-info/RECORD
